db2i_mcp_server/__init__.py
db2i_mcp_server/server.py
db2i_mcp_server-0.1.0.dist-info/METADATA
db2i_mcp_server-0.1.0.dist-info/WHEEL
db2i_mcp_server-0.1.0.dist-info/entry_points.txt
db2i_mcp_server-0.1.0.dist-info/RECORD
