Metadata-Version: 2.4
Name: db2i-mcp-server
Version: 0.1.0
Summary: A MCP server implementation for Db2 for i
Author-email: Adam Shedivy <ajshedivyaj@gmail.com>
Requires-Python: >=3.12
Requires-Dist: mapepire-python>=0.2.0
Requires-Dist: mcp[cli]>=1.3.0
